pyparamvalidate/__init__.py
pyparamvalidate/core/param_validator.py
pyparamvalidate/core/validator.py
pyparamvalidate/tests/test_param_validator.py
pyparamvalidate/tests/test_validator.py
pyparamvalidate/utils/dict_utils.py
pyparamvalidate-0.3.3.dist-info/METADATA
pyparamvalidate-0.3.3.dist-info/WHEEL
pyparamvalidate-0.3.3.dist-info/licenses/LICENSE
pyparamvalidate-0.3.3.dist-info/RECORD
