Metadata-Version: 2.1
Name: pyparamvalidate
Version: 0.3.3
Summary: 一个简单易用的 Python 函数参数校验装饰器。提供多种内置验证器，支持自定义验证规则，帮助开发者轻松进行函数参数校验。
Project-URL: homepage, https://github.com/xyouwen/pyparamvalidate
Author-email: kindtester <kindtester@foxmail.com>
License-File: LICENSE
Classifier: License :: OSI Approved :: MIT License
Classifier: Operating System :: OS Independent
Classifier: Programming Language :: Python :: 3
Requires-Python: >=3.9
Requires-Dist: pytest
Requires-Dist: schema
